{"name": "manga", "isRoot": "yes", "children": [{"isMedia": "yes", "name": "manga", "children": [{"isGenre": "yes", "name": "supernatural", "children": [{"isTheme": "yes", "name": "school", "children": [{"isMovie": "yes", "name": "Reborn!"}, {"isMovie": "yes", "name": "Teizokurei Monophobia"}, {"isMovie": "yes", "name": "Ai-kagi"}, {"isMovie": "yes", "name": "Ayakashi Hisen"}, {"isMovie": "yes", "name": "Blue Exorcist"}, {"isMovie": "yes", "name": "Another"}, {"isMovie": "yes", "name": "Hells Angels"}]}]}]}]}