{"name": "anime", "isRoot": "yes", "children": [{"isMedia": "yes", "name": "TV", "children": [{"isGenre": "yes", "name": "comedy", "children": [{"isTheme": "yes", "name": "love triangle", "children": [{"isMovie": "yes", "name": "Love, Chunibyo & Other Delusions! -Heart Throb-"}, {"isMovie": "yes", "name": "Blue Spring Ride"}, {"isMovie": "yes", "name": "Aquarion Evol"}, {"isMovie": "yes", "name": "Baka and Test - Summon the Beasts 2"}, {"isMovie": "yes", "name": "Kasimasi - Girl Meets Girl"}, {"isMovie": "yes", "name": "Boys Over Flowers"}, {"isMovie": "yes", "name": "Jewelpet Sunshine"}, {"isMovie": "yes", "name": "Kimagure Orange Road"}, {"isMovie": "yes", "name": "Mikagura School Suite"}]}]}]}]}