{"name": "anime", "isRoot": "yes", "children": [{"isMedia": "yes", "name": "TV", "children": [{"isGenre": "yes", "name": "comedy", "children": [{"isTheme": "yes", "name": "magical girl", "children": [{"isMovie": "yes", "name": "Sugar Sugar Rune"}, {"isMovie": "yes", "name": "Demashitaa! Powerpuff Girls Z"}, {"isMovie": "yes", "name": "Ojamajo Doremi DOKKAAN!"}, {"isMovie": "yes", "name": "Mermaid Melody: Pichi Pichi Pitch"}, {"isMovie": "yes", "name": "Gakuen Alice"}, {"isMovie": "yes", "name": "Getsumen to Heiki Mina"}, {"isMovie": "yes", "name": "My-Otome"}, {"isMovie": "yes", "name": "Jewelpet Kira\u2606Deco\u2014!"}, {"isMovie": "yes", "name": "Ojamajo Doremi #"}, {"isMovie": "yes", "name": "Nanaka 6/17"}, {"isMovie": "yes", "name": "Mirmo Zibang!"}, {"isMovie": "yes", "name": "Momokyun Sword"}, {"isMovie": "yes", "name": "Cardcaptor Sakura"}, {"isMovie": "yes", "name": "Fate/kaleid liner Prisma Illya"}, {"isMovie": "yes", "name": "Dokidoki! Precure"}, {"isMovie": "yes", "name": "Is This a Zombie?"}, {"isMovie": "yes", "name": "Mo~tto! Ojamajo Doremi"}, {"isMovie": "yes", "name": "Lil' Red Riding Hood Cha-Cha"}, {"isMovie": "yes", "name": "Magical Project S"}, {"isMovie": "yes", "name": "Fresh Pretty Cure"}, {"isMovie": "yes", "name": "Ultra Maniac"}, {"isMovie": "yes", "name": "Nurse Witch Komugi R"}, {"isMovie": "yes", "name": "Futari wa Pretty Cure"}, {"isMovie": "yes", "name": "Tokyo Mew Mew"}]}]}]}]}