{"name": "manga", "isRoot": "yes", "children": [{"isMedia": "yes", "name": "magazine", "children": [{"isGenre": "yes", "name": "No Genre", "children": [{"isTheme": "yes", "name": "all", "children": [{"isMovie": "yes", "name": "Action Pizazz DX"}, {"isMovie": "yes", "name": "Manga Time Family"}, {"isMovie": "yes", "name": "ARIA"}, {"isMovie": "yes", "name": "Penguin Club Sanzokuban"}, {"isMovie": "yes", "name": "Doki!"}, {"isMovie": "yes", "name": "Comic P Flirt"}, {"isMovie": "yes", "name": "Comic MegaPlus"}, {"isMovie": "yes", "name": "Namaiki!"}, {"isMovie": "yes", "name": "Bessatsu Sh\u014dnen Champion"}, {"isMovie": "yes", "name": "Comic Avarus"}, {"isMovie": "yes", "name": "Comic MegaCube"}, {"isMovie": "yes", "name": "Weekly Shonen Sunday"}, {"isMovie": "yes", "name": "Comic Nyan\u00b2 Club GOLD"}, {"isMovie": "yes", "name": "Yha! Hip&Lip"}, {"isMovie": "yes", "name": "Comic BomBom"}, {"isMovie": "yes", "name": "Dragon Junior"}, {"isMovie": "yes", "name": "Melody"}, {"isMovie": "yes", "name": "Moba Man"}, {"isMovie": "yes", "name": "Comic Kurofune"}]}]}]}]}