{"ratings": [{"ratings": "7.832", "anime": {"name": "Cardcaptor Sakura"}}, {"ratings": "7.4359", "anime": {"name": "Is This a Zombie?"}}, {"ratings": "7.274", "anime": {"name": "Magic Knight Rayearth 2"}}, {"ratings": "7.1337", "anime": {"name": "Sailor Moon R"}}, {"ratings": "7.0162", "anime": {"name": "Sugar Sugar Rune"}}, {"ratings": "6.9094", "anime": {"name": "Mirmo Zibang!"}}, {"ratings": "6.9042", "anime": {"name": "Ultra Maniac"}}, {"ratings": "6.8879", "anime": {"name": "Lil' Red Riding Hood Cha-Cha"}}, {"ratings": "6.7994", "anime": {"name": "Nanaka 6/17"}}, {"ratings": "6.293", "anime": {"name": "Tokyo Mew Mew"}}, {"ratings": "6.2043", "anime": {"name": "Mermaid Melody: Pichi Pichi Pitch"}}, {"ratings": "5.9014", "anime": {"name": "Kagihime Monogatari - Eikyuu Alice Rondo"}}, {"ratings": "5.5926", "anime": {"name": "Dr. Rin ni Kiitemite!"}}]}